diff2latex/__init__.py
diff2latex/__main__.py
diff2latex/api.py
diff2latex/cli.py
diff2latex/core/__init__.py
diff2latex/core/diff2latex.py
diff2latex/core/models/__init__.py
diff2latex/core/models/cell.py
diff2latex/core/models/code.py
diff2latex/core/models/line.py
diff2latex/core/utils/__init__.py
diff2latex/core/utils/colorizer.py
diff2latex/core/utils/colormap.py
diff2latex/templates/template.tex
diff2latex-0.1.0.dist-info/licenses/LICENSE
diff2latex-0.1.0.dist-info/METADATA
diff2latex-0.1.0.dist-info/WHEEL
diff2latex-0.1.0.dist-info/entry_points.txt
diff2latex-0.1.0.dist-info/top_level.txt
diff2latex-0.1.0.dist-info/RECORD
