Metadata-Version: 2.4
Name: diff2latex
Version: 0.1.0
Summary: Simple utility that produces diffs in a LaTeX format
Home-page: https://github.com/divadiahim/diff2latex
Author: divadiahim
Author-email: 
Maintainer: divadiahim
License: MIT
Project-URL: Homepage, https://github.com/divadiahim/diff2latex
Project-URL: Repository, https://github.com/divadiahim/diff2latex
Project-URL: Bug Reports, https://github.com/divadiahim/diff2latex/issues
Keywords: diff,latex,pdf,git,version-control,documentation
Classifier: Development Status :: 3 - Alpha
Classifier: Intended Audience :: Developers
Classifier: Topic :: Software Development :: Build Tools
Classifier: Topic :: Text Processing :: Markup :: LaTeX
Classifier: License :: OSI Approved :: MIT License
Classifier: Programming Language :: Python :: 3
Classifier: Programming Language :: Python :: 3.7
Classifier: Programming Language :: Python :: 3.8
Classifier: Programming Language :: Python :: 3.9
Classifier: Programming Language :: Python :: 3.10
Classifier: Programming Language :: Python :: 3.11
Classifier: Programming Language :: Python :: 3.12
Classifier: Operating System :: OS Independent
Requires-Python: >=3.7
License-File: LICENSE
Requires-Dist: click>=8.0.0
Requires-Dist: pydantic>=2.0.0
Requires-Dist: Pygments>=2.0.0
Requires-Dist: typing-extensions>=4.0.0
Provides-Extra: dev
Requires-Dist: pytest; extra == "dev"
Requires-Dist: black; extra == "dev"
Requires-Dist: isort; extra == "dev"
Requires-Dist: mypy; extra == "dev"
Dynamic: home-page
Dynamic: license-file
Dynamic: requires-python
